[{"Name": "Shane Watson", "Age": 40, "Birthplace": "Ipswich, Queenslan", "Role": "Batting Allrounder", "Bat": "Right Handed Bat", "Bowl": "Right-arm fast-medium", "Teams": "Australia, Rajasthan Royals, New South Wales, Sydney Sixers, Brisbane Heat, Australians, Hobart Hurricanes, Canterbury, Sydney Thunder, Islamabad United, Royal Challengers Bangalore, Saint Lucia Kings, Dhaka Dynamites, Chennai Super Kings, Quetta Gladiators, Sindhis, Amsterdam Knights, Deccan Gladiators, Rangpur Rangers, Gilchrist XI", "Wicket": "48", "Run": "5757", "Bio": "To conquer international cricket,Shane Watson first had to beat his fragile body,Despite boasting an athletic figure made for photo shoots,Watson's frame was so brittle it threatened to break him,He refused to give up,Not through recurrences of back stress fractures,a dislocated shoulder or a suspected heart attack that turned out to be food poisoning,He changed his training,preferring pilates to weights,It finally paid off in 2009,when he was chosen as a Test opener in the middle of the Ashes series,Many batsmen would have been uncomfortable with the promotion from the middle order,especially after failing when given the job with Queensl,but Watson had become used to re-inventing himself,With a history of setbacks,it was not a surprise that his first Test century became such a drama,but after two scores in the 90s  an 89,he finally brought it up at the MCG against Pakistan - thanks to a single from a dropped catch,He had earned some luck,A productive few years as a Test opener led to back-to-back Allan Border Medals but by 2011-12,injury had again interceded,He returned to the Test team in 2012 but spent the rest of his career floating up  down the order in search of a place to call his own,Watson became Australia's 44th Test captain when he led the team to a three-day loss in Delhi in place of the injured Michael Clarke,It completed a hectic couple of weeks for Watson,who had been suspended from the previous Test in the homework saga  had also flown home for the birth of his child,He gave up the vice-captaincy after that tour  played for another two years before being dropped during the 2015 Ashes,after which he announced his retirement from Tests,Watson developed into one of Australia's best exponents of reverse swing,if he was not claiming wickets himself he was often building pressure at one end,At times his bowling saved his place in the Test team,for four centuries from 59 Tests  an average of 35,19 was a little less than he desired as a batsman,At the crease he is an aggressive brute with a broad chest,a right-hed disciple of Matthew Hayden,someone who often doesn't need to follow-through to gain a boundary,his drives  pulls are delivered in a much smoother style,Always a dangerous striker in the shorter formats,Watson clubbed Bangladesh for 185 in a 50-over contest in April 2011,the highest score ever by an Australian batsman in ODI cricket,The Player of the Tournament at the 2012 World T20,Watson retired from all international cricket at the end of the 2016 tournament,\n<br/><b>ESPNcricinfo staff</b>"}]